fdk_rdf_parser/__init__.py
fdk_rdf_parser/classes/__init__.py
fdk_rdf_parser/classes/address.py
fdk_rdf_parser/classes/agent.py
fdk_rdf_parser/classes/business_event.py
fdk_rdf_parser/classes/catalog.py
fdk_rdf_parser/classes/channel.py
fdk_rdf_parser/classes/concept.py
fdk_rdf_parser/classes/conforms_to.py
fdk_rdf_parser/classes/contactpoint.py
fdk_rdf_parser/classes/cost.py
fdk_rdf_parser/classes/cpsvno_service.py
fdk_rdf_parser/classes/data_distribution_service.py
fdk_rdf_parser/classes/dataservice.py
fdk_rdf_parser/classes/dataset.py
fdk_rdf_parser/classes/dcat_resource.py
fdk_rdf_parser/classes/dct_standard.py
fdk_rdf_parser/classes/distribution.py
fdk_rdf_parser/classes/event.py
fdk_rdf_parser/classes/evidence.py
fdk_rdf_parser/classes/exceptions.py
fdk_rdf_parser/classes/format.py
fdk_rdf_parser/classes/harvest_meta_data.py
fdk_rdf_parser/classes/info_model.py
fdk_rdf_parser/classes/legal_resource.py
fdk_rdf_parser/classes/life_event.py
fdk_rdf_parser/classes/media_type.py
fdk_rdf_parser/classes/model_element.py
fdk_rdf_parser/classes/model_property.py
fdk_rdf_parser/classes/organization.py
fdk_rdf_parser/classes/output.py
fdk_rdf_parser/classes/participation.py
fdk_rdf_parser/classes/public_service.py
fdk_rdf_parser/classes/publisher.py
fdk_rdf_parser/classes/qualified_attribution.py
fdk_rdf_parser/classes/quality_annotation.py
fdk_rdf_parser/classes/reference_data_code.py
fdk_rdf_parser/classes/references.py
fdk_rdf_parser/classes/requirement.py
fdk_rdf_parser/classes/rule.py
fdk_rdf_parser/classes/skos_concept.py
fdk_rdf_parser/classes/subject.py
fdk_rdf_parser/classes/temporal.py
fdk_rdf_parser/classes/theme.py
fdk_rdf_parser/classes/types.py
fdk_rdf_parser/fdk_rdf_parser.py
fdk_rdf_parser/parse_functions/__init__.py
fdk_rdf_parser/parse_functions/address.py
fdk_rdf_parser/parse_functions/agent.py
fdk_rdf_parser/parse_functions/catalog.py
fdk_rdf_parser/parse_functions/channel.py
fdk_rdf_parser/parse_functions/concept.py
fdk_rdf_parser-2.9.0.dist-info/LICENSE
fdk_rdf_parser-2.9.0.dist-info/METADATA
fdk_rdf_parser-2.9.0.dist-info/WHEEL
fdk_rdf_parser-2.9.0.dist-info/RECORD
