Metadata-Version: 2.1
Name: fdk-rdf-parser
Version: 2.9.0
Summary: 
Author: NilsOveTen
Author-email: nils.ove.tendenes@digdir.no
Requires-Python: >=3.9,<4.0
Classifier: Programming Language :: Python :: 3
Classifier: Programming Language :: Python :: 3.9
Classifier: Programming Language :: Python :: 3.10
Classifier: Programming Language :: Python :: 3.11
Classifier: Programming Language :: Python :: 3.12
Classifier: Programming Language :: Python :: 3.13
Requires-Dist: isodate (>=0.7.2,<0.8.0)
Requires-Dist: rdflib (>=7.2.1,<8.0.0)
Requires-Dist: requests (>=2.32.5,<3.0.0)
